setup.cfg
setup.py
django_call_prevention/__init__.py
django_call_prevention/decorators.py
django_call_prevention.egg-info/PKG-INFO
django_call_prevention.egg-info/SOURCES.txt
django_call_prevention.egg-info/dependency_links.txt
django_call_prevention.egg-info/top_level.txt