Metadata-Version: 1.0
Name: django-call-prevention
Version: 0.1.1
Summary: Mocks calls automatically during testing time
Home-page: https://github.com/Sebubu/django-call-prevention
Author: Severin Bühler
Author-email: sevi_buehler@hotmail.com
License: MIT
Keywords: django,decorators,testing,mock,reusable
Platform: UNKNOWN
